kotatsu/__init__.py
kotatsu-0.0.1.dist-info/METADATA
kotatsu-0.0.1.dist-info/WHEEL
kotatsu-0.0.1.dist-info/top_level.txt
kotatsu-0.0.1.dist-info/RECORD
