Metadata-Version: 2.1
Name: kotatsu
Version: 0.0.1
Summary: Testing hello world
Home-page: UNKNOWN
Author: Kotatsu
Author-email: <nikitakotatsu@gmail.com>
License: UNKNOWN
Platform: UNKNOWN
Classifier: Development Status :: 1 - Planning
Classifier: Intended Audience :: Developers
Classifier: Programming Language :: Python :: 3
Classifier: Operating System :: Unix
Classifier: Operating System :: MacOS :: MacOS X
Classifier: Operating System :: Microsoft :: Windows
